onepiece_interpreter.py
onepiece_lang-0.1.6.dist-info/METADATA
onepiece_lang-0.1.6.dist-info/WHEEL
onepiece_lang-0.1.6.dist-info/entry_points.txt
onepiece_lang-0.1.6.dist-info/top_level.txt
onepiece_lang-0.1.6.dist-info/RECORD
