Metadata-Version: 2.4
Name: onepiece-lang
Version: 0.1.6
Summary: OnePiece Language: A fun, themed programming language inspired by One Piece
Home-page: https://github.com/yourusername/onepiece-lang
Author: Hash
Author-email: website2k5@gmail.com
Keywords: programming-language,one-piece,interpreter,streamlit
Classifier: Programming Language :: Python :: 3
Classifier: Programming Language :: Python :: 3.8
Classifier: Programming Language :: Python :: 3.9
Classifier: Programming Language :: Python :: 3.10
Classifier: Programming Language :: Python :: 3.11
Classifier: License :: OSI Approved :: MIT License
Classifier: Operating System :: OS Independent
Requires-Python: >=3.8
Requires-Dist: click>=8.0
Requires-Dist: streamlit>=1.0
Dynamic: author
Dynamic: author-email
Dynamic: classifier
Dynamic: description-content-type
Dynamic: home-page
Dynamic: keywords
Dynamic: requires-dist
Dynamic: requires-python
Dynamic: summary
